PyEdit/PyEditxN.py
PyEdit/__init__.py
PyEdit/_functions.py
PyEdit/function.py
PyEdit-1.8.0.data/data/bin/PyEdit.c
PyEdit-1.8.0.data/data/bin/pyedit
PyEdit-1.8.0.data/data/share/PyEdit/Data/custom_theme.css
PyEdit-1.8.0.data/data/share/PyEdit/Data/pyedit.png
PyEdit-1.8.0.data/data/share/PyEdit/Data/theme.xml
PyEdit-1.8.0.data/data/share/PyEdit/Data/ui.ui
PyEdit-1.8.0.data/data/share/PyEdit/Data/128x128/pyedit.png
PyEdit-1.8.0.data/data/share/PyEdit/Data/256x256/pyedit.png
PyEdit-1.8.0.data/data/share/applications/PyEdit.desktop
PyEdit-1.8.0.data/data/share/icons/hicolor/128x128/apps/pyedit.png
PyEdit-1.8.0.data/data/share/icons/hicolor/256x256/apps/pyedit.png
PyEdit-1.8.0.data/data/share/icons/hicolor/512x512/apps/pyedit.png
PyEdit-1.8.0.data/data/share/icons/hicolor/64x64/apps/pyedit.png
pyedit/PyEditxN.py
pyedit/__init__.py
pyedit/_functions.py
pyedit/function.py
PyEdit-1.8.0.dist-info/AUTHORS
PyEdit-1.8.0.dist-info/COPYING
PyEdit-1.8.0.dist-info/METADATA
PyEdit-1.8.0.dist-info/WHEEL
PyEdit-1.8.0.dist-info/top_level.txt
PyEdit-1.8.0.dist-info/RECORD
