Metadata-Version: 2.1
Name: PyEdit
Version: 1.8.0
Summary: A Python Editor using GTK
Home-page: UNKNOWN
Author: AstralDev
Author-email: ekureedem480@gmail.com
License: LGPL
Keywords: editor development
Platform: UNKNOWN
Classifier: Development Status :: 4 - Beta
Classifier: Environment :: X11 Applications :: GTK
Classifier: Intended Audience :: Developers
Requires-Python: >=3
Requires-Dist: PyGObject
Requires-Dist: autopep8
Requires-Dist: jedi
Requires-Dist: markdown
